[
    {
        "years": 2024
    },
    {
        "years": 2023
    },
    {
        "years": 2022
    },
    {
        "years": 2021
    },
    {
        "years": 2020
    },
    {
        "years": 2018
    },
    {
        "years": 2017
    },
    {
        "years": 2016
    },
    {
        "years": 2015
    },
    {
        "years": 2014
    },
    {
        "years": 2013
    },
    {
        "years": 2012
    },
    {
        "years": 2011
    },
    {
        "years": 2010
    },
    {
        "years": 2009
    },
    {
        "years": 2008
    },
    {
        "years": 2007
    },
    {
        "years": 2006
    },
    {
        "years": 2005
    },
    {
        "years": 2004
    },
    {
        "years": 2003
    },
    {
        "years": 2002
    },
    {
        "years": 2001
    },
    {
        "years": 2000
    },
    {
        "years": 1999
    },
    {
        "years": 1998
    },
    {
        "years": 1997
    },
    {
        "years": 1996
    },
    {
        "years": 1995
    },
    {
        "years": 1994
    },
    {
        "years": 1993
    },
    {
        "years": 1992
    },
    {
        "years": 1991
    },
    {
        "years": 1990
    },
    {
        "years": 1989
    },
    {
        "years": 1988
    },
    {
        "years": 1987
    },
    {
        "years": 1986
    },
    {
        "years": 1984
    }
]